CyvoreOS/Scan.py
CyvoreOS/Template_plugin.py
CyvoreOS/__init__.py
CyvoreOS/checkObject.py
CyvoreOS/checkTypes.py
CyvoreOS/checkUtils.py
CyvoreOS/regex_patterns.py
CyvoreOS/Plugins/abuseIPDB_plugin.py
CyvoreOS/Plugins/cryptoWalletValidator_plugin.py
CyvoreOS/Plugins/top500domains.txt
CyvoreOS/Plugins/virusTotal_plugin.py
CyvoreOS/Plugins/whois_plugin.py
CyvoreOS/Resources/top500domains.txt
CyvoreOS/Resources/top500urls.txt
CyvoreOS/interfaces/right_click_install.py
CyvoreOS-0.2.dist-info/METADATA
CyvoreOS-0.2.dist-info/WHEEL
CyvoreOS-0.2.dist-info/top_level.txt
CyvoreOS-0.2.dist-info/RECORD
