Metadata-Version: 2.1
Name: CyvoreOS
Version: 0.2
Summary: Next-Gen email threat prevention
Home-page: https://cyvore.com
Download-URL: https://github.com/cyvore/CyvoreOS/archive/refs/tags/v_0.1.7.6.6.tar.gz
Author: Cyvore
Author-email: info@cyvore.com
License: MIT
Keywords: Anti-Phishing,Email-Scanner,Optical-Recognition
Classifier: Development Status :: 3 - Alpha
Classifier: Intended Audience :: Developers
Classifier: Topic :: Software Development :: Build Tools
Classifier: License :: OSI Approved :: MIT License
Classifier: Programming Language :: Python :: 3
Requires-Dist: levenshtein
Requires-Dist: requests
Requires-Dist: colorama
Requires-Dist: future
Requires-Dist: urlextract
Requires-Dist: blockcypher
Requires-Dist: urlexpander
Requires-Dist: python-whois
Requires-Dist: eml-parser
Requires-Dist: python-magic
Requires-Dist: extract-msg
Requires-Dist: vt-py
